CPR/__init__.py
CPR/analysis.py
CPR/annuities.py
CPR/assets.py
CPR/balance_sheets.py
CPR/debts.py
CPR/initialisation.py
CPR/macro.py
CPR/main.py
CPR/simulator.py
CPR/taxes.py
CPR/tools.py
CPR/data/inputs/synth_inputs.csv
CPR/data/params/common_params.csv
CPR/data/params/diff_log_wage.csv
CPR/data/params/inflation.csv
CPR/data/params/mix_fee_assets.csv
CPR/data/params/mix_fee_debt.csv
CPR/data/params/prices.csv
CPR/data/params/rrif_rates.csv
CPR/data/params/user_options.csv
CPR/data/params/ympe.csv
CPR/data/precomputed/d_factors.pickle
CPR/life/__init__.py
CPR/life/life.py
CPR/life/params/ab_females.xlsx
CPR/life/params/ab_males.xlsx
CPR/life/params/bc_females.xlsx
CPR/life/params/bc_males.xlsx
CPR/life/params/mb_females.xlsx
CPR/life/params/mb_males.xlsx
CPR/life/params/nb_females.xlsx
CPR/life/params/nb_males.xlsx
CPR/life/params/nl_females.xlsx
CPR/life/params/nl_males.xlsx
CPR/life/params/ns_females.xlsx
CPR/life/params/ns_males.xlsx
CPR/life/params/nt_females.xlsx
CPR/life/params/nt_males.xlsx
CPR/life/params/on_females.xlsx
CPR/life/params/on_males.xlsx
CPR/life/params/pe_females.xlsx
CPR/life/params/pe_males.xlsx
CPR/life/params/qc_females.xlsx
CPR/life/params/qc_males.xlsx
CPR/life/params/quotients.xlsx
CPR/life/params/sk_females.xlsx
CPR/life/params/sk_males.xlsx
cpr_rsi-1.2.2.dist-info/LICENSE
cpr_rsi-1.2.2.dist-info/METADATA
cpr_rsi-1.2.2.dist-info/WHEEL
cpr_rsi-1.2.2.dist-info/top_level.txt
cpr_rsi-1.2.2.dist-info/RECORD
