Metadata-Version: 2.1
Name: cpr-rsi
Version: 1.2.2
Summary: Assessing Canadians' Preparation for Retirement
Home-page: https://rsi-models.github.io/CPR/en
Author: Team RSI
Author-email: pyanni@gmail.com
License: MIT
Platform: UNKNOWN
Classifier: Programming Language :: Python :: 3
Classifier: License :: OSI Approved :: MIT License
Classifier: Operating System :: OS Independent
Requires-Python: >=3.6
Requires-Dist: pandas
Requires-Dist: numpy
Requires-Dist: requests
Requires-Dist: statsmodels
Requires-Dist: srpp
Requires-Dist: srd
